megaphone/__init__.py
megaphone/client.py
megaphone/errors.py
megaphone/network.py
megaphone/organization.py
megaphone/test/__init__.py
megaphone/test/test_linting.py
megaphone-0.2.0.dist-info/METADATA
megaphone-0.2.0.dist-info/RECORD
megaphone-0.2.0.dist-info/WHEEL
megaphone-0.2.0.dist-info/top_level.txt
