Metadata-Version: 2.1
Name: megaphone
Version: 0.2.0
Summary: Connect to the megaphone.fm API
Home-page: http://github.com/theatlantic/megaphone
Author: Brian Muller
Author-email: bmuller@theatlantic.com
License: MIT
Platform: UNKNOWN
Requires-Dist: requests (>~2.19.1)
Requires-Dist: yarl (>~1.2.6)
